<?xml version='1.0' encoding='utf-8'?>
<text id="uTWtdwzzxaM" uploader="Joe Fazer" channel="Joe Fazer" likes="130319" title="I Travelled To Afghanistan... And Left Within 3 hours" year="2025" month="10" day="22" is_ac="true">
  <u t="6080">Okay, here goes nothing. This trip was</u>
  <u t="9760">stepping out of my comfort zone. I was</u>
  <u t="11200">on my way to Afghanistan, a country now</u>
  <u t="13280">ruled and run by the Taliban,</u>
  <u t="14719">statistically the most dangerous country</u>
  <u t="16240">in the world and a place which is just</u>
  <u t="18160">advised not to go. [music] But I wanted</u>
  <u t="20480">to see the real side of Afghanistan, not</u>
  <u t="22240">just what you hear online. The idea was</u>
  <u t="24160">to spend 5 days there. No bad agenda</u>
  <u t="26320">whatsoever. just me traveling around,</u>
  <u t="28400">meeting locals, trying the [music] food,</u>
  <u t="31359">but it didn't go to plan. I left the</u>
  <u t="33200">country within 24 hours of being there.</u>
  <u t="35440">Let me let me explain why. But just</u>
  <u t="37200">before I want to clarify, this is not</u>
  <u t="38719">like a hate video. No one is to blame</u>
  <u t="40879">but myself for this. You know, I made</u>
  <u t="42559">the decision to enter someone else's</u>
  <u t="44079">country where they have their own rules</u>
  <u t="45680">and regulations and everything that led</u>
  <u t="47600">up to it was ultimately my decision. I'm</u>
  <u t="50239">my own person and I I take</u>
  <u t="51680">responsibility for it. Anyway, with all</u>
  <u t="53520">that out of the way, let me take you to</u>
  <u t="55039">the very start of the trip where</u>
  <u t="56480">everything started to unfold</u>
  <u t="62160">in Istanbul, which is our connection to</u>
  <u t="64559">Kabul, the capital of Afghanistan.</u>
  <u t="66640">That's where we're going. After a few</u>
  <u t="68720">hours of waiting, we boarded the final</u>
  <u t="70320">plane, a 4-hour flight from Istanbul to</u>
  <u t="72960">Kabul.</u>
  <u t="75520">As the flight got near, I remember this</u>
  <u t="77600">being the most nervous I'd been. Are you</u>
  <u t="79759">getting nervous?</u>
  <u t="81680">Um, yeah, a little bit. I'm going to be</u>
  <u t="84640">honest. Yeah. Yeah. Same. I just don't</u>
  <u t="87680">know like what to expect when I get to</u>
  <u t="90240">the airport. You know what I mean?</u>
  <u t="94321">[music] Eventually, the flight pulled</u>
  <u t="95759">in. We've made it.</u>
  <u t="98240">I walked through the airport into</u>
  <u t="99920">airport security. And at this point, I'm</u>
  <u t="102000">now officially on their land. So, nerves</u>
  <u t="104720">were even higher. I started to overthink</u>
  <u t="106880">everything. And as I walked up to the</u>
  <u t="108799">airport border control,</u>
  <u t="112079">&gt;&gt; no, just see see the place. Look around.</u>
  <u t="120399">&gt;&gt; They were completely fine. There was no</u>
  <u t="122079">issues whatsoever.</u>
  <u t="124960">&gt;&gt; Thank you, bro.</u>
  <u t="125759">&gt;&gt; As we were getting to the final security</u>
  <u t="127520">checkpoint, a member of Taliban came</u>
  <u t="129759">over to us.</u>
  <u t="130800">&gt;&gt; Excuse me. Hello. How are you?</u>
  <u t="132160">&gt;&gt; How you doing? Good.</u>
  <u t="134239">&gt;&gt; Nice to meet you. I'm Joe.</u>
  <u t="135440">&gt;&gt; Nice to meet you. Where do we go first?</u>
  <u t="137760">&gt;&gt; We go we stay in Kabul for a bit.</u>
  <u t="139760">&gt;&gt; Okay.</u>
  <u t="140000">&gt;&gt; And then we go see those lakes.</u>
  <u t="141360">&gt;&gt; Kabul too.</u>
  <u t="142160">&gt;&gt; Are we leaving? Yeah. Yeah. Yeah.</u>
  <u t="144319">&gt;&gt; Good to meet you guys.</u>
  <u t="146959">&gt;&gt; Have a nice trip.</u>
  <u t="148160">&gt;&gt; He was super friendly towards us and</u>
  <u t="149996">[music] that continued like leaving the</u>
  <u t="152400">airport. All the locals were starting</u>
  <u t="154160">conversations with us. They were asking</u>
  <u t="155920">if we needed help, offering us to use</u>
  <u t="157599">their phones. Like the hospitality was</u>
  <u t="160160">amazing. We've made it. Welcome to</u>
  <u t="162319">Afghanistan.</u>
  <u t="165200">How you doing?</u>
  <u t="166480">&gt;&gt; You good, Joe? Nice to meet you. We met</u>
  <u t="168239">up with our tour guide, Manm [music]</u>
  <u t="169200">Moon, and he was honestly such a sound,</u>
  <u t="171360">kind, genuine guy. I'm a travel guide in</u>
  <u t="174160">Afghanistan. And now I'm busy with the</u>
  <u t="177040">nice guys. [music]</u>
  <u t="182092">[music]</u>
  <u t="182319">&gt;&gt; We first got checked into the hotel.</u>
  <u t="187519">&gt;&gt; Very nice.</u>
  <u t="190480">&gt;&gt; Really? Nice to meet you. How you doing?</u>
  <u t="192720">Nice to meet you. Look at this. This is</u>
  <u t="195680">beautiful. How you doing?</u>
  <u t="197680">&gt;&gt; You good? Nice to meet you, man. Nice to</u>
  <u t="199519">meet you, man.</u>
  <u t="201519">&gt;&gt; Thank you very much. Thank you.</u>
  <u t="203760">&gt;&gt; Amazing, man. Thank you very much. Nice</u>
  <u t="206000">to meet you.</u>
  <u t="206400">&gt;&gt; Here we are. As the flight was pulling</u>
  <u t="208640">in, I was pretty [music] nervous, I'll</u>
  <u t="210319">be honest. And as soon as like I spoke</u>
  <u t="212239">to the first person that worked at the</u>
  <u t="214000">airport, my nerves went like so far.</u>
  <u t="217440">Everyone has been so nice. My moon told</u>
  <u t="219280">us to change into the [music] local</u>
  <u t="220400">clothing. This one is</u>
  <u t="223599">This is what we've been told to wear.</u>
  <u t="225280">And Jack is I rate it.</u>
  <u t="228400">&gt;&gt; Jack is a fan. You</u>
  <u t="229360">&gt;&gt; like it?</u>
  <u t="229920">&gt;&gt; Let's head out into the city of Kabul.</u>
  <u t="237840">&gt;&gt; The first location we came to [music]</u>
  <u t="239280">was this giant Taliban flag. And as I'm</u>
  <u t="241519">sure you can imagine, there were tons of</u>
  <u t="242879">Taliban around it.</u>
  <u t="243840">&gt;&gt; The camera there.</u>
  <u t="245599">&gt;&gt; Again, they were all incredibly friendly</u>
  <u t="247280">towards us.</u>
  <u t="248239">&gt;&gt; How are you?</u>
  <u t="249200">&gt;&gt; We're good, man. Very good.</u>
  <u t="250480">&gt;&gt; Thank you. Alice, that is crazy.</u>
  <u t="252640">Impressive.</u>
  <u t="254080">&gt;&gt; We were making good conversation. In</u>
  <u t="255920">fact, one of them asked for my number</u>
  <u t="257759">and he sent me like loads of Afghanistan</u>
  <u t="260160">memes.</u>
  <u t="261919">You just wouldn't expect that.</u>
  <u t="266000">But yeah, things were positive at this</u>
  <u t="268160">point. We were in a we're in a good good</u>
  <u t="269840">mood.</u>
  <u t="273040">But this is where things took a slight</u>
  <u t="275440">Uturn.</u>
  <u t="278240">As we left that area, we headed to the</u>
  <u t="280240">streets [music] of Kabal.</u>
  <u t="282240">&gt;&gt; Where are we now?</u>
  <u t="283280">&gt;&gt; We are going to go inside of the crime.</u>
  <u t="285600">&gt;&gt; Okay.</u>
  <u t="287440">&gt;&gt; We came to this beautiful mosque which</u>
  <u t="289120">our tour [music] guide recommended and</u>
  <u t="290400">we wanted to check out. Guarding it,</u>
  <u t="292000">however, were some officials. Officials</u>
  <u t="294080">are just like Taliban members, security.</u>
  <u t="296800">They spotted [music] us instantly and</u>
  <u t="299280">one of them started searching me.</u>
  <u t="302960">What is this? It's a microphone.</u>
  <u t="308000">You see, I was wearing a microphone like</u>
  <u t="309759">I do whenever [music] I film, and he</u>
  <u t="311360">didn't like that.</u>
  <u t="312000">&gt;&gt; Do you have journalist visa?</u>
  <u t="313840">&gt;&gt; No, I didn't. I only had a tourist visa.</u>
  <u t="316720">You see, this is a bit of a gray area</u>
  <u t="318080">because filming a YouTube video on one</u>
  <u t="320080">hand can be seen as a journalist video,</u>
  <u t="322000">but on the other hand, it can just be</u>
  <u t="323280">seen as, you know, making a innocent</u>
  <u t="324960">tourist YouTube video. Before [music]</u>
  <u t="326400">the trip, I did a ton of due diligence</u>
  <u t="327919">on this. Um, I spoke to companies who</u>
  <u t="330160">have organized trips here before, and</u>
  <u t="331840">they said, "Look, a tourist visa is</u>
  <u t="333759">fine. You don't need a journalist visa."</u>
  <u t="335680">But now I was actually in the country.</u>
  <u t="337520">That didn't seem to be the case. It it</u>
  <u t="339199">seemed to be a problem. When the</u>
  <u t="340400">microphone had been spotted, I could</u>
  <u t="342160">sense tensions [music]</u>
  <u t="343120">kind of rose a little bit. The official</u>
  <u t="345520">was speaking back and forth with my tour</u>
  <u t="347039">guide. They were making sure that the</u>
  <u t="348463">[music] camera lenses were fully</u>
  <u t="349680">blocked. They took our passports and</u>
  <u t="351600">took photos of them and they basically</u>
  <u t="353039">just said, "Look, you can't film."</u>
  <u t="354320">Eventually, my tour guide managed to</u>
  <u t="355759">deescalate the situation and I just</u>
  <u t="358080">thought it was best that we got out of</u>
  <u t="359520">that area. What What happened to those</u>
  <u t="361440">two YouTubers? Um, so now I think they</u>
  <u t="364880">are in uh in jail something. Why?</u>
  <u t="368479">&gt;&gt; Because it's against of the rule of</u>
  <u t="370240">these guys. I'm talking about these</u>
  <u t="372880">guys. You mean the officials?</u>
  <u t="374720">&gt;&gt; So the officials spotted the YouTubers</u>
  <u t="377039">and then they sent them to jail.</u>
  <u t="379440">&gt;&gt; Well, that's quite scary.</u>
  <u t="380880">&gt;&gt; Yeah, of course.</u>
  <u t="382479">&gt;&gt; How long How long were they put in jail</u>
  <u t="384160">for?</u>
  <u t="385600">&gt;&gt; Maybe for 3 months something. 3 months.</u>
  <u t="388000">&gt;&gt; Yeah. This was not what I wanted to hear</u>
  <u t="390400">after what had just happened.</u>
  <u t="392000">Apparently, like very recently, as in</u>
  <u t="394400">within the last couple days, there were</u>
  <u t="396160">new rules put in by the Taliban in</u>
  <u t="397919">regards to filming.</u>
  <u t="398960">&gt;&gt; And you heard about the YouTubers who</u>
  <u t="400560">got put in jail.</u>
  <u t="401759">&gt;&gt; Yeah. Yeah.</u>
  <u t="402479">&gt;&gt; Why did they get put in jail?</u>
  <u t="404080">&gt;&gt; They didn't have the permits.</u>
  <u t="405520">&gt;&gt; They didn't have the right permits.</u>
  <u t="406960">&gt;&gt; The government, they think between the</u>
  <u t="409440">tourist people, there are some spies.</u>
  <u t="412080">&gt;&gt; Spies?</u>
  <u t="412720">&gt;&gt; Yeah. I was panicking a little bit at</u>
  <u t="414319">this point because, you know, my</u>
  <u t="415840">passport's just been scanned and I</u>
  <u t="417759">technically don't have the right permit.</u>
  <u t="419520">So, I said to the tour guide, "Look, can</u>
  <u t="420800">we just go somewhere a bit quieter, a</u>
  <u t="422720">bit more out the way?"</u>
  <u t="427280">We are heading now to an amusement park</u>
  <u t="429280">here in Afghanistan.</u>
  <u t="432000">As we walked in, it was like a ghost</u>
  <u t="433919">town, but there was one other person,</u>
  <u t="435680">another official.</u>
  <u t="438560">&gt;&gt; Wow, look at this. Hello.</u>
  <u t="440720">&gt;&gt; Hello. How you doing?</u>
  <u t="469280">At this point, I didn't know what was</u>
  <u t="470639">going on. Um the official was speaking</u>
  <u t="472800">back and forth with my tour guide in the</u>
  <u t="474560">local language. He was also going on</u>
  <u t="476800">call and speaking to other people.</u>
  <u t="479199">&gt;&gt; And I remember just saying to my tour</u>
  <u t="480960">guide like what what's going on? And his</u>
  <u t="484050">[snorts] reply is what just scared me</u>
  <u t="486560">and and it was the main reasons why we</u>
  <u t="488560">got out of there. I asked what's going</u>
  <u t="489919">on and he replied they're starting an</u>
  <u t="492639">investigation on you. When we heard that</u>
  <u t="495360">like me and my cameraman Jack just</u>
  <u t="497120">looked at each other obviously thinking</u>
  <u t="499599">the worst. You said that they they want</u>
  <u t="501520">to investigate us.</u>
  <u t="502720">&gt;&gt; Yeah.</u>
  <u t="503520">&gt;&gt; Okay. That's not good. All right. I</u>
  <u t="506160">think um I think me and Jack we might we</u>
  <u t="509440">might get a flight home just because if</u>
  <u t="511759">we're not allowed to video like</u>
  <u t="514800">there's probably not much point and we</u>
  <u t="516399">don't want to risk going to jail and all</u>
  <u t="518000">of that. You know what I mean? So we</u>
  <u t="519519">might have to buy a flight today, get</u>
  <u t="521839">and get out of here.</u>
  <u t="524399">Just I just don't want to take the risk.</u>
  <u t="525920">You know, you telling me about the</u>
  <u t="527120">YouTubers who got put in jail. Like we</u>
  <u t="529120">don't want to we don't want to risk that</u>
  <u t="530720">&gt;&gt; as a normal tourist. You can film your</u>
  <u t="533440">&gt;&gt; Yeah. But we just don't want to risk it.</u>
  <u t="535279">&gt;&gt; Yeah.</u>
  <u t="535519">&gt;&gt; Anyway, we got back to the hotel and we</u>
  <u t="537519">spoke to our travel guide on his opinion</u>
  <u t="539200">on what we should do.</u>
  <u t="540240">&gt;&gt; Just just go just let's get out of</u>
  <u t="541680">there.</u>
  <u t="542160">&gt;&gt; Yeah.</u>
  <u t="542640">&gt;&gt; You think?</u>
  <u t="543040">&gt;&gt; Yeah. Yeah. Yeah. 100% 100%.</u>
  <u t="544560">&gt;&gt; I want to say look, there's a very high</u>
  <u t="546160">likelihood we would have been completely</u>
  <u t="547760">fine. I just didn't want to take the</u>
  <u t="549120">risk.</u>
  <u t="549839">&gt;&gt; I don't think we want to push it push it</u>
  <u t="551760">to the limit where it ends up coming</u>
  <u t="553680">back and biting us.</u>
  <u t="554640">&gt;&gt; So, we booked the next available flight</u>
  <u t="556399">which was early that next morning.</u>
  <u t="568480">You nervous</u>
  <u t="569920">&gt;&gt; a little bit. I I'm just like they're</u>
  <u t="572720">going to wonder why are we leaving so</u>
  <u t="574000">soon?</u>
  <u t="574399">&gt;&gt; That's Yeah.</u>
  <u t="575440">&gt;&gt; And then if we are flagged up plus</u>
  <u t="577680">leaving so soon like that's not a good</u>
  <u t="580399">look.</u>
  <u t="580800">&gt;&gt; No, exactly. That's what I'm thinking.</u>
  <u t="582399">&gt;&gt; Okay, off we go. On the way to the</u>
  <u t="585519">airport, I was worrying a little bit</u>
  <u t="587200">because in my head [music] I was</u>
  <u t="588480">thinking, one, are they not going to be</u>
  <u t="590560">suspicious that we're leaving within 24</u>
  <u t="592560">hours of getting there? And two, if our</u>
  <u t="594320">passports get scanned, are we going to</u>
  <u t="595920">flag up on the system [music] because of</u>
  <u t="597360">what happened the day before? As we made</u>
  <u t="599040">our way through the airport, the nerves</u>
  <u t="600399">were very high, but just wanted to act</u>
  <u t="602160">as [music] calm and composed as</u>
  <u t="603920">possible. And then I made it to border</u>
  <u t="606240">control. This was the moment of truth. I</u>
  <u t="608880">handed him my passport, and as [music]</u>
  <u t="610480">he scanned it,</u>
  <u t="613120">we were completely fine. He ushered me</u>
  <u t="614959">on my way and uh got the flight back.</u>
  <u t="621760">We're leaved. Now, to end this video, I</u>
  <u t="624160">want to say, look, there's a very high</u>
  <u t="625600">likelihood we would have been completely</u>
  <u t="627200">fine. The people of Afghanistan were</u>
  <u t="629360">lovely. I genuinely believe if you're</u>
  <u t="631360">just going there to be a tourist, you'll</u>
  <u t="632959">be completely fine. There'll be no</u>
  <u t="634560">issues, but ultimately, we'd gone into</u>
  <u t="636480">that country. We didn't know if we were</u>
  <u t="638560">breaking the rules or not, and we just</u>
  <u t="640240">didn't want to take the risk. It's as</u>
  <u t="641839">simple as that. Yeah, I'm definitely</u>
  <u t="643200">going to travel to Afghanistan again at</u>
  <u t="644880">some point in the future, like</u>
  <u t="645839">non-filming because I really want to</u>
  <u t="647680">explore the country. But um that is why</u>
  <u t="651440">we left Afghanistan so soon after</u>
  <u t="653839">getting there. Thank you guys for</u>
  <u t="655120">watching.</u>
  </text>
